<?xml version="1.0" encoding="utf-8" ?>
<dwsync>
<file name="orange.png" server="C:/xampp/htdocs/2014/" local="128050442200000000" remote="128050442200000000" Dst="2" />
<file name="main1.png" server="C:/xampp/htdocs/2014/" local="130409111052234751" remote="130409111050000000" Dst="2" />
<file name="menu.png" server="C:/xampp/htdocs/2014/" local="128018679560000000" remote="128018679560000000" Dst="2" />
<file name="site_logo.jpg" server="C:/xampp/htdocs/2014/" local="130409420656648677" remote="130409420650000000" Dst="2" />
<file name="orange_menu.png" server="C:/xampp/htdocs/2014/" local="128018681360000000" remote="128018681360000000" Dst="2" />
<file name="orange_sbi.png" server="C:/xampp/htdocs/2014/" local="128018692400000000" remote="128018692400000000" Dst="2" />
<file name="link.png" server="C:/xampp/htdocs/2014/" local="128019367780000000" remote="128019367780000000" Dst="2" />
<file name="style.css" server="C:/xampp/htdocs/2014/" local="130411856553560912" remote="130411856550000000" Dst="2" />
<file name="orange.css" server="C:/xampp/htdocs/2014/" local="130409454896477083" remote="130409454890000000" Dst="2" />
<file name="graphic.jpg" server="C:/xampp/htdocs/2014/" local="128042761840000000" remote="128042761840000000" Dst="2" />
</dwsync>